Metadata-Version: 1.0
Name: wisdomnuggets
Version: 1.3
Summary: The wisest maxim in the world
Home-page: https://github.com/ss1921
Author: 1921Designs
Author-email: im1921designs@gmail.com
License: MIT
Platform: UNKNOWN
